pytest_notify.py
pytest_notify-0.1.4.dist-info/entry_points.txt
pytest_notify-0.1.4.dist-info/LICENSE
pytest_notify-0.1.4.dist-info/WHEEL
pytest_notify-0.1.4.dist-info/METADATA
pytest_notify-0.1.4.dist-info/RECORD
