Metadata-Version: 1.2
Name: pytest_notify
Version: 0.1.4
Summary: Get notifications when your tests ends
Home-page: https://github.com/Shir0kamii/pytest_notify
License: UNKNOWN
Author: Alexandre Bonnetain
Author-email: alexandrebonnetain@gmail.com
Classifier: License :: OSI Approved :: MIT License
Requires-Dist: pytest>=3.0.0
